{
  "users":[{
    "name": "SONIA",
    "pass": "2264",
    "household": "a"
    },
    {
    "name": "OSCAR",
    "pass": "1761",
    "household": "a"
    },
    {
    "name": "LUCIA",
    "pass": "password",
    "household": "a"
    },
    {
    "name": "TOMAS",
    "pass": "soytonto",
    "household": "a"
    },
    {
    "name": "NOEMI",
    "pass": "1234",
     "household": "b"
    },
    {
    "name": "ANDRES",
    "pass": "0778",
    "household": "c"
    },
    {
    "name": "LUCAS",
    "pass": "10",
     "household": "c"
    },
    {
    "name": "INES",
    "pass": "0203",
    "household": "d"
    },
    {
    "name": "LUIS",
    "pass": "1302",
        "household": "d"
    },
    {
    "name": "MIRIAM",
    "pass": "0218",
        "household": "e"
    },
    {
    "name": "CECI",
    "pass": "0911",
        "household": "e"
    }
    ]
}
